{
  "id": "quiz-8",
  "title": "Quiz - O Poder da Repetição",
  "description": "Teste seus conhecimentos sobre loops e estruturas de repetição em JavaScript.",
  "timeLimit": 900,
  "questions": [
    {
      "id": "q1",
      "question": "Qual é o propósito fundamental dos loops na programação?",
      "alternatives": [
        {
          "id": "a1",
          "text": "Tornar o código mais complexo",
          "isCorrect": false,
          "explanation": "Loops não existem para adicionar complexidade, mas para simplificar tarefas repetitivas."
        },
        {
          "id": "a2",
          "text": "Automatizar a execução repetitiva de código de forma eficiente",
          "isCorrect": true,
          "explanation": "Correto! Loops são fundamentais porque permitem automatizar tarefas repetitivas, executando o mesmo código múltiplas vezes de forma eficiente."
        },
        {
          "id": "a3",
          "text": "Criar variáveis automáticas",
          "isCorrect": false,
          "explanation": "Loops não criam variáveis automáticas, eles executam código repetidamente."
        },
        {
          "id": "a4",
          "text": "Acelerar a execução de programas",
          "isCorrect": false,
          "explanation": "Loops não aceleram programas por si só, eles automatizam tarefas repetitivas."
        }
      ]
    },
    {
      "id": "q2",
      "question": "Qual conceito diferencia principalmente o loop 'while' do 'do...while'?",
      "alternatives": [
        {
          "id": "a1",
          "text": "A velocidade de execução",
          "isCorrect": false,
          "explanation": "A performance é praticamente a mesma entre os dois tipos de loop."
        },
        {
          "id": "a2",
          "text": "O momento da verificação da condição (antes vs. depois da primeira execução)",
          "isCorrect": true,
          "explanation": "Correto! while verifica a condição antes de executar (pode nunca executar), enquanto do...while verifica depois (sempre executa pelo menos uma vez)."
        },
        {
          "id": "a3",
          "text": "O tipo de variáveis que podem usar",
          "isCorrect": false,
          "explanation": "Ambos os loops podem usar os mesmos tipos de variáveis."
        },
        {
          "id": "a4",
          "text": "A complexidade das operações permitidas",
          "isCorrect": false,
          "explanation": "Ambos permitem as mesmas operações dentro do loop."
        }
      ]
    },
    {
      "id": "q3",
      "question": "Por que o loop 'for' é considerado mais compacto que o 'while'?",
      "alternatives": [
        {
          "id": "a1",
          "text": "É mais rápido na execução",
          "isCorrect": false,
          "explanation": "A performance é similar entre for e while."
        },
        {
          "id": "a2",
          "text": "Reúne inicialização, condição e incremento em uma única declaração",
          "isCorrect": true,
          "explanation": "Correto! O loop for concentra os três componentes essenciais (inicialização, condição e atualização) em uma única linha."
        },
        {
          "id": "a3",
          "text": "Usa menos memória",
          "isCorrect": false,
          "explanation": "O uso de memória é similar entre os diferentes tipos de loop."
        },
        {
          "id": "a4",
          "text": "É mais fácil de entender para iniciantes",
          "isCorrect": false,
          "explanation": "A facilidade de entendimento é subjetiva e depende do contexto."
        }
      ]
    },
    {
      "id": "q4",
      "question": "Qual princípio explica por que loops infinitos devem ser evitados?",
      "alternatives": [
        {
          "id": "a1",
          "text": "Usam mais memória que o necessário",
          "isCorrect": false,
          "explanation": "O problema principal não é o uso de memória, mas a execução indefinida."
        },
        {
          "id": "a2",
          "text": "Podem travar o programa ao nunca satisfazer a condição de parada",
          "isCorrect": true,
          "explanation": "Correto! Loops infinitos são problemáticos porque nunca satisfazem a condição de parada, fazendo o programa executar indefinidamente."
        },
        {
          "id": "a3",
          "text": "São incompatíveis com navegadores modernos",
          "isCorrect": false,
          "explanation": "Navegadores executam loops infinitos, mas isso pode travá-los."
        },
        {
          "id": "a4",
          "text": "Causam erros de sintaxe",
          "isCorrect": false,
          "explanation": "Loops infinitos não causam erros de sintaxe, eles são sintaticamente corretos."
        }
      ]
    },
    {
      "id": "q5",
      "question": "Por que a escolha entre diferentes tipos de loop depende do contexto do problema?",
      "alternatives": [
        {
          "id": "a1",
          "text": "Para mostrar conhecimento técnico avançado",
          "isCorrect": false,
          "explanation": "A escolha deve ser baseada na clareza e adequação ao problema."
        },
        {
          "id": "a2",
          "text": "Cada tipo é otimizado para diferentes padrões de controle de iteração",
          "isCorrect": true,
          "explanation": "Correto! for é melhor quando você sabe o número de iterações, while para condições complexas, e do...while quando precisa executar pelo menos uma vez."
        },
        {
          "id": "a3",
          "text": "Para compatibilidade com versões antigas do JavaScript",
          "isCorrect": false,
          "explanation": "Todos os tipos de loop são suportados em todas as versões do JavaScript."
        },
        {
          "id": "a4",
          "text": "Para economizar linhas de código",
          "isCorrect": false,
          "explanation": "A economia de código não é o principal motivo da escolha."
        }
      ]
    },
    {
      "id": "q6",
      "question": "Qual conceito fundamental todos os loops compartilham?",
      "alternatives": [
        {
          "id": "a1",
          "text": "Devem usar a mesma sintaxe exata",
          "isCorrect": false,
          "explanation": "Cada tipo de loop tem sua própria sintaxe específica."
        },
        {
          "id": "a2",
          "text": "Execução repetitiva controlada por uma condição de parada",
          "isCorrect": true,
          "explanation": "Correto! Todos os loops executam código repetidamente até que uma condição de parada seja satisfeita."
        },
        {
          "id": "a3",
          "text": "Sempre usam números como contadores",
          "isCorrect": false,
          "explanation": "Loops podem usar qualquer tipo de condição, não apenas números."
        },
        {
          "id": "a4",
          "text": "Executam exatamente 10 vezes",
          "isCorrect": false,
          "explanation": "Loops podem executar qualquer número de vezes, dependendo da condição."
        }
      ]
    },
    {
      "id": "q7",
      "question": "Por que usar nomes descritivos para variáveis de controle de loop é importante?",
      "alternatives": [
        {
          "id": "a1",
          "text": "Para impressionar outros programadores",
          "isCorrect": false,
          "explanation": "Nomes descritivos são sobre clareza, não sobre impressionar."
        },
        {
          "id": "a2",
          "text": "Para melhorar legibilidade e manutenibilidade do código",
          "isCorrect": true,
          "explanation": "Correto! Nomes descritivos tornam o código mais legível e fácil de manter, facilitando entendimento futuro."
        },
        {
          "id": "a3",
          "text": "Para usar mais memória do sistema",
          "isCorrect": false,
          "explanation": "Nomes de variáveis não afetam significativamente o uso de memória."
        },
        {
          "id": "a4",
          "text": "É obrigatório em JavaScript moderno",
          "isCorrect": false,
          "explanation": "Não é obrigatório, mas é uma boa prática recomendada."
        }
      ]
    },
    {
      "id": "q8",
      "question": "Qual princípio orienta a otimização de performance em loops?",
      "alternatives": [
        {
          "id": "a1",
          "text": "Sempre usar o loop com menos caracteres",
          "isCorrect": false,
          "explanation": "O tamanho do código não determina a performance."
        },
        {
          "id": "a2",
          "text": "Minimizar cálculos repetitivos desnecessários dentro do loop",
          "isCorrect": true,
          "explanation": "Correto! A principal otimização é evitar cálculos desnecessários que são repetidos em cada iteração."
        },
        {
          "id": "a3",
          "text": "Usar apenas variáveis globais",
          "isCorrect": false,
          "explanation": "Variáveis globais não melhoram performance e podem causar problemas."
        },
        {
          "id": "a4",
          "text": "Evitar usar qualquer função dentro do loop",
          "isCorrect": false,
          "explanation": "Funções podem ser usadas dentro de loops quando necessário."
        }
      ]
    },
    {
      "id": "q9",
      "question": "Qual conceito fundamental explica por que loops aninhados devem ser usados com cautela?",
      "alternatives": [
        {
          "id": "a1",
          "text": "Loops aninhados são proibidos em JavaScript moderno",
          "isCorrect": false,
          "explanation": "Loops aninhados são perfeitamente permitidos em JavaScript."
        },
        {
          "id": "a2",
          "text": "Loops aninhados criam complexidade multiplicativa no número de iterações",
          "isCorrect": true,
          "explanation": "Correto! Um loop de 100 iterações dentro de outro de 100 resulta em 10.000 execuções, impactando performance."
        },
        {
          "id": "a3",
          "text": "Loops aninhados sempre causam erros de sintaxe",
          "isCorrect": false,
          "explanation": "Loops aninhados são sintaticamente válidos quando bem escritos."
        },
        {
          "id": "a4",
          "text": "Loops aninhados ocupam mais espaço no disco rígido",
          "isCorrect": false,
          "explanation": "O tamanho do código é irrelevante para o problema de performance."
        }
      ]
    },
    {
      "id": "q10",
      "question": "Qual princípio fundamental explica a intercambialidade entre diferentes tipos de loops?",
      "alternatives": [
        {
          "id": "a1",
          "text": "Todos resolvem o mesmo problema fundamental: repetição controlada",
          "isCorrect": true,
          "explanation": "Correto! Os diferentes tipos de loops são ferramentas intercambiáveis para repetição controlada. A escolha é sobre clareza de código."
        },
        {
          "id": "a2",
          "text": "Todos executam na mesma velocidade em qualquer situação",
          "isCorrect": false,
          "explanation": "A performance pode variar dependendo da situação específica."
        },
        {
          "id": "a3",
          "text": "Todos são processados da mesma forma internamente pelo JavaScript",
          "isCorrect": false,
          "explanation": "JavaScript pode otimizar diferentes tipos de loop de formas diferentes."
        },
        {
          "id": "a4",
          "text": "Todos devem ser evitados em código de produção",
          "isCorrect": false,
          "explanation": "Loops são essenciais e amplamente usados em código de produção."
        }
      ]
    }
  ]
}
